pubtools/iib/__init__.py
pubtools/iib/iib_ops.py
pubtools/iib/utils.py
pubtools_iib-0.26.0.dist-info/METADATA
pubtools_iib-0.26.0.dist-info/WHEEL
pubtools_iib-0.26.0.dist-info/entry_points.txt
pubtools_iib-0.26.0.dist-info/top_level.txt
pubtools_iib-0.26.0.dist-info/RECORD
