Metadata-Version: 2.1
Name: pubtools-iib
Version: 0.26.0
Summary: Pubtools-iib
Home-page: https://gitlab.cee.redhat.com/jluza/pubtools-iib
Author: Jindrich Luza
Author-email: jluza@redhat.com
Classifier: Development Status :: 3 - Alpha
Classifier: Intended Audience :: Developers
Classifier: License :: OSI Approved :: GNU Lesser General Public License v3 (LGPLv3)
Classifier: Programming Language :: Python
Classifier: Programming Language :: Python :: 3
Classifier: Programming Language :: Python :: 3.7
Classifier: Programming Language :: Python :: Implementation :: CPython
Classifier: Programming Language :: Python :: Implementation :: PyPy
Requires-Python: >=3.6
Requires-Dist: setuptools
Requires-Dist: iiblib
Requires-Dist: pushcollector
Requires-Dist: requests
Provides-Extra: rest
Requires-Dist: Sphinx; extra == "rest"
